pixel2svgpkg/__init__.py
pixel2svgpkg/constants.py
pixel2svgpkg/py.typed
pixel2svgpkg/utils.py
pixel2svgpkg-0.1.0.dist-info/LICENSE
pixel2svgpkg-0.1.0.dist-info/WHEEL
pixel2svgpkg-0.1.0.dist-info/METADATA
pixel2svgpkg-0.1.0.dist-info/RECORD
