Metadata-Version: 2.1
Name: pixel2svgpkg
Version: 0.1.0
Summary: A Python package/fork from the pixel2svg project by Florian Berger.
Home-page: https://github.com/joaopalmeiro/pixel2svgpkg
License: GPL-3.0-only
Keywords: pixel2svgpkg
Author: João Palmeiro
Author-email: joaommpalmeiro@gmail.com
Requires-Python: >=3.6,<4.0
Classifier: Development Status :: 3 - Alpha
Classifier: Intended Audience :: Developers
Classifier: Intended Audience :: Information Technology
Classifier: Intended Audience :: Science/Research
Classifier: License :: OSI Approved :: GNU General Public License v3 (GPLv3)
Classifier: Natural Language :: English
Classifier: Operating System :: OS Independent
Classifier: Programming Language :: Python :: 3
Classifier: Programming Language :: Python :: 3.10
Classifier: Programming Language :: Python :: 3.6
Classifier: Programming Language :: Python :: 3.7
Classifier: Programming Language :: Python :: 3.8
Classifier: Programming Language :: Python :: 3.9
Classifier: Programming Language :: Python :: Implementation :: CPython
Classifier: Topic :: Software Development
Classifier: Topic :: Software Development :: Libraries
Classifier: Topic :: Software Development :: Libraries :: Python Modules
Classifier: Typing :: Typed
Requires-Dist: Pillow (>=8.4.0,<9.0.0)
Requires-Dist: importlib-metadata (>=1.0,<2.0); python_version < "3.8"
Requires-Dist: svgwrite (>=1.4.1,<2.0.0)
Project-URL: Bug Tracker, https://github.com/joaopalmeiro/pixel2svgpkg/issues
Project-URL: Repository, https://github.com/joaopalmeiro/pixel2svgpkg
Project-URL: Twitter, https://twitter.com/joaompalmeiro
